adafruit_dotstar.py
adafruit_circuitpython_dotstar-2.2.19.dist-info/licenses/LICENSE
adafruit_circuitpython_dotstar-2.2.19.dist-info/METADATA
adafruit_circuitpython_dotstar-2.2.19.dist-info/WHEEL
adafruit_circuitpython_dotstar-2.2.19.dist-info/top_level.txt
adafruit_circuitpython_dotstar-2.2.19.dist-info/RECORD
