Metadata-Version: 2.4
Name: adafruit-circuitpython-dotstar
Version: 2.2.19
Summary: CircuitPython library for DotStar LEDs.
Author-email: Adafruit Industries <circuitpython@adafruit.com>
License: MIT
Project-URL: Homepage, https://github.com/adafruit/Adafruit_CircuitPython_DotStar
Keywords: adafruit,dotstar,leds,rgb,spi,addressable,hardware,micropython,circuitpython
Classifier: Intended Audience :: Developers
Classifier: Topic :: Software Development :: Libraries
Classifier: Topic :: Software Development :: Embedded Systems
Classifier: Topic :: System :: Hardware
Classifier: License :: OSI Approved :: MIT License
Classifier: Programming Language :: Python :: 3
License-File: LICENSE
Requires-Dist: Adafruit-Blinka>=7.0.0
Requires-Dist: adafruit-circuitpython-typing
Requires-Dist: adafruit-circuitpython-pixelbuf
Provides-Extra: optional
Dynamic: license-file
